wnnet/__about__.py
wnnet/__init__.py
wnnet/consts.py
wnnet/flows.py
wnnet/graph.py
wnnet/graph_helper.py
wnnet/net.py
wnnet/nuc.py
wnnet/reac.py
wnnet/thermo.py
wnnet/zones.py
wnnet-2.7.0.dist-info/licenses/LICENSE.txt
wnnet-2.7.0.dist-info/METADATA
wnnet-2.7.0.dist-info/WHEEL
wnnet-2.7.0.dist-info/top_level.txt
wnnet-2.7.0.dist-info/RECORD
